here_location_services/__init__.py
here_location_services/__version__.py
here_location_services/apis.py
here_location_services/autosuggest_api.py
here_location_services/destination_weather_api.py
here_location_services/exceptions.py
here_location_services/geocoding_search_api.py
here_location_services/isoline_routing_api.py
here_location_services/ls.py
here_location_services/matrix_routing_api.py
here_location_services/responses.py
here_location_services/routing_api.py
here_location_services/utils.py
here_location_services/config/__init__.py
here_location_services/config/autosuggest_config.py
here_location_services/config/base_config.py
here_location_services/config/dest_weather_config.py
here_location_services/config/isoline_routing_config.py
here_location_services/config/matrix_routing_config.py
here_location_services/config/routing_config.py
here_location_services/config/search_config.py
here_location_services/config/url_config.py
here_location_services/platform/__init__.py
here_location_services/platform/auth.py
here_location_services/platform/credentials.py
here_location_services/platform/apis/__init__.py
here_location_services/platform/apis/aaa_oauth2_api.py
here_location_services/platform/apis/api.py
here_location_services-0.4.0.dist-info/LICENSE
here_location_services-0.4.0.dist-info/METADATA
here_location_services-0.4.0.dist-info/WHEEL
here_location_services-0.4.0.dist-info/top_level.txt
here_location_services-0.4.0.dist-info/RECORD
