Metadata-Version: 2.1
Name: here-location-services
Version: 0.4.0
Summary: HERE Location Services for Python
Home-page: https://here.com
Author: HERE Europe B.V.
License: Apache-2.0
Project-URL: Bug Tracker, https://github.com/heremaps/here-location-services-python/issues
Project-URL: Source, https://github.com/heremaps/here-location-services-python
Keywords: API,REST,Client,Locaton Services
Platform: any
Classifier: Development Status :: 4 - Beta
Classifier: Intended Audience :: Developers
Classifier: Topic :: Software Development :: Libraries
Classifier: License :: OSI Approved :: Apache Software License
Classifier: Operating System :: OS Independent
Classifier: Programming Language :: Python :: 3
Classifier: Programming Language :: Python :: 3 :: Only
Classifier: Programming Language :: Python :: 3.6
Classifier: Programming Language :: Python :: 3.7
Classifier: Programming Language :: Python :: 3.8
Classifier: Programming Language :: Python :: 3.9
Requires-Dist: requests
Requires-Dist: geojson
Requires-Dist: flexpolyline
Requires-Dist: pandas
Requires-Dist: pyhocon
Requires-Dist: requests-oauthlib
Provides-Extra: dev
Requires-Dist: coverage ; extra == 'dev'
Requires-Dist: black[jupyter] (>=21.8b0) ; extra == 'dev'
Requires-Dist: mypy ; extra == 'dev'
Requires-Dist: proxy.py ; extra == 'dev'
Requires-Dist: pytest ; extra == 'dev'
Requires-Dist: pytest-cov ; extra == 'dev'
Requires-Dist: pytest-mypy ; extra == 'dev'
Requires-Dist: twine ; extra == 'dev'
Requires-Dist: pytest-flake8 ; extra == 'dev'
Requires-Dist: isort ; extra == 'dev'
Requires-Dist: darglint ; extra == 'dev'
Requires-Dist: pytest-mock ; extra == 'dev'
Requires-Dist: types-requests ; extra == 'dev'
Requires-Dist: Sphinx (>=2.4.0) ; extra == 'dev'
Requires-Dist: sphinx-rtd-theme ; extra == 'dev'
Requires-Dist: jupyter-sphinx (==0.2.4a1) ; extra == 'dev'
Requires-Dist: here-map-widget-for-jupyter (>=1.1.1) ; extra == 'dev'
